silabs_mltk-0.20.0.data/purelib/mltk/__init__.py
silabs_mltk-0.20.0.data/purelib/mltk/__main__.py
silabs_mltk-0.20.0.data/purelib/mltk/cli/__init__.py
silabs_mltk-0.20.0.data/purelib/mltk/cli/classify_audio_mltk_cli.py
silabs_mltk-0.20.0.data/purelib/mltk/cli/classify_image_mltk_cli.py
silabs_mltk-0.20.0.data/purelib/mltk/cli/commander_mltk_cli.py
silabs_mltk-0.20.0.data/purelib/mltk/cli/compile_mltk_cli.py
silabs_mltk-0.20.0.data/purelib/mltk/cli/custom_mltk_cli.py
silabs_mltk-0.20.0.data/purelib/mltk/cli/evaluate_mltk_cli.py
silabs_mltk-0.20.0.data/purelib/mltk/cli/fingerprint_reader_mltk_cli.py
silabs_mltk-0.20.0.data/purelib/mltk/cli/main.py
silabs_mltk-0.20.0.data/purelib/mltk/cli/profile_mltk_cli.py
silabs_mltk-0.20.0.data/purelib/mltk/cli/quantize_mltk_cli.py
silabs_mltk-0.20.0.data/purelib/mltk/cli/ssh_mltk_cli.py
silabs_mltk-0.20.0.data/purelib/mltk/cli/summarize_mltk_cli.py
silabs_mltk-0.20.0.data/purelib/mltk/cli/tensorboard_mltk_cli.py
silabs_mltk-0.20.0.data/purelib/mltk/cli/train_mltk_cli.py
silabs_mltk-0.20.0.data/purelib/mltk/cli/update_params_mltk_cli.py
silabs_mltk-0.20.0.data/purelib/mltk/cli/utest_mltk_cli.py
silabs_mltk-0.20.0.data/purelib/mltk/cli/utils.py
silabs_mltk-0.20.0.data/purelib/mltk/cli/view_audio_mltk_cli.py
silabs_mltk-0.20.0.data/purelib/mltk/cli/view_mltk_cli.py
silabs_mltk-0.20.0.data/purelib/mltk/cli/tests/__init__.py
silabs_mltk-0.20.0.data/purelib/mltk/cli/tests/test_basic.py
silabs_mltk-0.20.0.data/purelib/mltk/cli/tests/test_classify_audio_cli.py
silabs_mltk-0.20.0.data/purelib/mltk/cli/tests/test_classify_image_cli.py
silabs_mltk-0.20.0.data/purelib/mltk/cli/tests/test_commander_cli.py
silabs_mltk-0.20.0.data/purelib/mltk/cli/tests/test_evaluate_cli.py
silabs_mltk-0.20.0.data/purelib/mltk/cli/tests/test_fingerprint_reader_cli.py
silabs_mltk-0.20.0.data/purelib/mltk/cli/tests/test_profile_cli.py
silabs_mltk-0.20.0.data/purelib/mltk/cli/tests/test_quantize_cli.py
silabs_mltk-0.20.0.data/purelib/mltk/cli/tests/test_ssh_cli.py
silabs_mltk-0.20.0.dist-info/LICENSE.md
silabs_mltk-0.20.0.dist-info/METADATA
silabs_mltk-0.20.0.dist-info/WHEEL
silabs_mltk-0.20.0.dist-info/entry_points.txt
silabs_mltk-0.20.0.dist-info/top_level.txt
silabs_mltk-0.20.0.dist-info/RECORD
