Metadata-Version: 2.1
Name: silabs-mltk
Version: 0.20.0
Summary: This allows for developing embedded machine learning models using Tensorflow-Lite Micro
Home-page: https://siliconlabs.github.io/mltk
Author: Silicon Labs
License: SPDX-License-Identifier: Zlib
Platform: UNKNOWN
Classifier: Programming Language :: Python :: 3.9
Classifier: Programming Language :: Python :: 3.10
Classifier: Programming Language :: Python :: 3.11
Classifier: Programming Language :: Python :: 3.12
Requires-Python: >=3.9,<3.13
License-File: LICENSE.md
Requires-Dist: typer <1.0
Requires-Dist: pytest
Requires-Dist: pytest-dependency
Requires-Dist: pytest-html-reporter
Requires-Dist: cmake
Requires-Dist: ninja
Requires-Dist: psutil
Requires-Dist: pyaml <22.0
Requires-Dist: tensorflow <2.17,>=2.3
Requires-Dist: tf-keras
Requires-Dist: tensorflow-probability >=0.12.2
Requires-Dist: tflite-support
Requires-Dist: protobuf <4.0,>=3.18
Requires-Dist: scipy <2.0
Requires-Dist: matplotlib <4.0
Requires-Dist: tqdm <5.0
Requires-Dist: pillow <11.0
Requires-Dist: librosa <1.0
Requires-Dist: bincopy <18.0
Requires-Dist: pyserial <4.0
Requires-Dist: GPUtil <2.0
Requires-Dist: patool ==1.12
Requires-Dist: prettytable <3.0,>=2.0
Requires-Dist: msgpack
Requires-Dist: numpy <1.23
Requires-Dist: flatbuffers <2.0
Provides-Extra: full
Requires-Dist: opencv-python ; extra == 'full'
Requires-Dist: netron ; extra == 'full'
Requires-Dist: paramiko ; extra == 'full'
Requires-Dist: cryptography ; extra == 'full'
Requires-Dist: tensorboard-plugin-profile ; extra == 'full'
Requires-Dist: onnx <1.11 ; extra == 'full'
Requires-Dist: onnxruntime ; extra == 'full'
